pymusicbox/__init__.py
pymusicbox/audio/__init__.py
pymusicbox/audio/audio.py
pymusicbox/symbolic/__init__.py
pymusicbox/symbolic/symbols.py
pymusicbox/synth/__init__.py
pymusicbox/synth/instrument/__init__.py
pymusicbox/synth/instrument/instrument.py
pymusicbox/synth/instrument/oscillator.py
pymusicbox-0.0.3.dist-info/LICENSE
pymusicbox-0.0.3.dist-info/METADATA
pymusicbox-0.0.3.dist-info/WHEEL
pymusicbox-0.0.3.dist-info/top_level.txt
pymusicbox-0.0.3.dist-info/RECORD
