Metadata-Version: 2.1
Name: pymusicbox
Version: 0.0.3
Summary: Toolkit with music synthesis and analysis tools for python.
Author: Maanas Arora
Maintainer: Maanas Arora
License: MIT License
Project-URL: Repository, https://github.com/MaanasArora/pymusicbox
Keywords: music
Classifier: Programming Language :: Python
Classifier: Operating System :: OS Independent
Requires-Python: >=3.8
License-File: LICENSE
Requires-Dist: cffi ==1.15.1
Requires-Dist: numpy ==1.23.5
Requires-Dist: pycparser ==2.21
Requires-Dist: soundfile ==0.11.0
